autodiff/__init__.py
autodiff/auto_diff.py
autodiff/dual_numbers.py
autodiff/functions.py
autodiff_cs107_bjmms-0.0.3.dist-info/LICENSE
autodiff_cs107_bjmms-0.0.3.dist-info/METADATA
autodiff_cs107_bjmms-0.0.3.dist-info/WHEEL
autodiff_cs107_bjmms-0.0.3.dist-info/top_level.txt
autodiff_cs107_bjmms-0.0.3.dist-info/RECORD
