Metadata-Version: 2.1
Name: autodiff-cs107-bjmms
Version: 0.0.3
Summary: Package for automatic differentiation
Author-email: Martin Reyes Holguin <mreyes@college.harvard.edu>, Marcos Rios Contreras <mrioscontreras@college.harvard.edu>, Sergio Jara Reynoso <sjarareynoso@college.harvard.edu>, Yumi Yi <yumiyi@college.harvard.edu>, Brian Medrano <brianmedrano@college.harvard.edu>
Project-URL: Homepage, https://harvard-iacs.github.io/2022-CS107/
Classifier: Programming Language :: Python :: 3
Classifier: License :: OSI Approved :: MIT License
Classifier: Topic :: Scientific/Engineering :: Mathematics
Requires-Python: >=3.9
License-File: LICENSE
